adawat/__init__.py
adawat/adaat.py
adawat/affix_const.py
adawat/generate.py
adawat/latex.py
adawat/myrepr.py
adawat/randtext.py
adawat-0.1.dist-info/DESCRIPTION.rst
adawat-0.1.dist-info/METADATA
adawat-0.1.dist-info/RECORD
adawat-0.1.dist-info/WHEEL
adawat-0.1.dist-info/metadata.json
adawat-0.1.dist-info/top_level.txt
