Metadata-Version: 2.0
Name: adawat
Version: 0.1
Summary: Adawat: Arabic Language Toolkit
Home-page: http://adawat.sourceforge.net/
Author: Taha Zerrouki
Author-email: taha.zerrouki@gmail.com
License: GPL
Platform: UNKNOWN
Classifier: Development Status :: 5 - Production/Stable
Classifier: Intended Audience :: End Users/Desktop
Classifier: Operating System :: OS Independent
Classifier: Programming Language :: Python
Requires-Dist: asmai (>=0.1)
Requires-Dist: mishkal (>=0.3)
Requires-Dist: naftawayh (>=0.4)
Requires-Dist: pyarabic (>=0.6.8)
Requires-Dist: qalsadi (>=0.3.6)
Requires-Dist: repr (>=0.3.1)
Requires-Dist: sylajone (>=0.2)
Requires-Dist: tashaphyne (>=0.3.4.1)
